rtl/skid_buffer.v
module skid_buffer #(
 parameter DATA_WIDTH = 32
)(
 input clk,
 input rst_n,
 
 //slave side (from master) //input interface
 input s_valid,
 output reg s_ready,
 input [DATA_WIDTH-1:0] s_data,

 //master side(to arbiter) //output interface
 output reg m_valid,
 input m_ready,
 output reg [DATA_WIDTH-1:0] m_data
);

reg skid_valid;
reg [DATA_WIDTH-1:0] skid_data;

always@(posedge clk or negedge rst_n) begin
 if(!rst_n) begin
  s_ready <= 1'b1;
  m_valid <=1'b0;
  m_data<={DATA_WIDTH{1'b0}};
  skid_valid <= 1'b0;
  skid_data <= {DATA_WIDTH{1'b0}};
 end else begin

 if (m_ready) begin
  if(skid_valid) begin
   m_valid <=1'b1;
   m_data<=skid_data;
   skid_valid <=1'b0;

 end else if (s_valid) begin
  m_valid <= 1'b1;
  m_data <= s_data;
 end
 else begin
  m_valid <= 1'b0;
 end
end
else begin
 if (s_valid && s_ready && !skid_valid) begin
  skid_valid <= 1'b1;
  skid_data <= s_data;
 end
end

if(skid_valid && !(m_ready)) begin
 s_ready <= 1'b0;
end else begin
 s_ready <= 1'b1;
end
end
end
endmodule

tb/tb_skid_buffer.v
module tb_skid_buffer;

parameter DATA_WIDTH = 32;

reg clk;
reg rst_n;
reg s_valid;
reg [DATA_WIDTH-1:0] s_data;
wire s_ready;
wire m_valid;
reg m_ready;
wire [DATA_WIDTH-1:0] m_data;

skid_buffer #(
 .DATA_WIDTH(DATA_WIDTH)
) dut(
 clk,
 rst_n,
 s_valid,
 s_ready,
 s_data,
 m_valid,
 m_ready,
 m_data
);

initial clk =0;
always #5 clk=~clk;

initial begin
 $dumpfile("sim/tb_skid_buffer.vcd");
 $dumpvars(0,tb_skid_buffer);
end

task send_beat;
    input [DATA_WIDTH-1:0] data;
    begin
        @(negedge clk);          // set data on falling edge
        s_valid = 1;
        s_data  = data;
        @(posedge clk);          // wait for rising edge
        while (!s_ready) begin
            @(posedge clk);
        end
        @(negedge clk);
        s_valid = 0;
    end
endtask

initial begin
 rst_n=0;
 s_valid=0;
 s_data=0;
 m_ready=1;
 #22;
 rst_n =1;
 #10;
 
 //Test 1 : downstream always ready

 $display("Test 1");
 send_beat(32'hAAAA_0001);
 send_beat(32'hBBBB_0002);
 send_beat(32'hCCCC_0003); 
 #20;
 $display("DONE test 1");

 //Downstream stalls

 $display("Test 2");
 m_ready = 0;
 s_valid=1;
 s_data=32'hDEAD_0001;
 #10;
 s_valid=1;
 s_data=32'hCAFE_B112;
 #10;
 m_ready=1;
 #30;
 s_valid = 0;
 #20;
 $display("done test 2");
 
 //back to back transfer

 $display("test 3");
 repeat(8) begin
  s_valid = 1;
  s_data= $random;
  #10;
 end
 s_valid=0;
 #30
$display("done test 3");

//reset during active tranfer
 
 $display("test 4");
 s_valid=1;
 s_data=32'hFFFF_FFFF;
 m_ready = 0;
 #10;
 rst_n=0;
 #4;
 rst_n=1;
 s_valid=0;
 m_ready=1;
 #20;
 $display("done");
 $finish;
end

always @(posedge clk) begin
 if(m_valid && m_ready)
  $display("t=%0t | TRANSFER m_data=0x%08h", $time, m_data);
 if(s_valid && !s_ready)
  $display("t=%0t | BACKPRESSURE s_data=0x%08h held", $time, s_data);
end

endmodule

sim/tb_skid_buffer.vcd
$date
	Fri Jun  5 12:45:08 2026
$end
$version
	Icarus Verilog
$end
$timescale
	1s
$end
$scope module tb_skid_buffer $end
$var wire 1 ! s_ready $end
$var wire 1 " m_valid $end
$var wire 32 # m_data [31:0] $end
$var reg 1 $ clk $end
$var reg 1 % m_ready $end
$var reg 1 & rst_n $end
$var reg 32 ' s_data [31:0] $end
$var reg 1 ( s_valid $end
$scope module dut $end
$var wire 1 $ clk $end
$var wire 1 % m_ready $end
$var wire 1 & rst_n $end
$var wire 32 ) s_data [31:0] $end
$var wire 1 ( s_valid $end
$var reg 32 * m_data [31:0] $end
$var reg 1 " m_valid $end
$var reg 1 ! s_ready $end
$var reg 32 + skid_data [31:0] $end
$var reg 1 , skid_valid $end
$upscope $end
$scope task send_beat $end
$var reg 32 - data [31:0] $end
$upscope $end
$upscope $end
$enddefinitions $end
#0
$dumpvars
bx -
0,
b0 +
b0 *
b0 )
0(
b0 '
0&
1%
0$
b0 #
0"
1!
$end
#5
1$
#10
0$
#15
1$
#20
0$
#22
1&
#25
1$
#30
0$
#32
b10101010101010100000000000000001 -
#35
1$
#40
b10101010101010100000000000000001 '
b10101010101010100000000000000001 )
1(
0$
#45
b10101010101010100000000000000001 #
b10101010101010100000000000000001 *
1"
1$
#50
b10111011101110110000000000000010 -
0(
0$
#55
0"
1$
#60
b10111011101110110000000000000010 '
b10111011101110110000000000000010 )
1(
0$
#65
b10111011101110110000000000000010 #
b10111011101110110000000000000010 *
1"
1$
#70
b11001100110011000000000000000011 -
0(
0$
#75
0"
1$
#80
b11001100110011000000000000000011 '
b11001100110011000000000000000011 )
1(
0$
#85
b11001100110011000000000000000011 #
b11001100110011000000000000000011 *
1"
1$
#90
0(
0$
#95
0"
1$
#100
0$
#105
1$
#110
0$
b11011110101011010000000000000001 '
b11011110101011010000000000000001 )
1(
0%
#115
b11011110101011010000000000000001 +
1,
1$
#120
0$
b11001010111111101011000100010010 '
b11001010111111101011000100010010 )
#125
0!
1$
#130
0$
1%
#135
1!
0,
b11011110101011010000000000000001 #
b11011110101011010000000000000001 *
1"
1$
#140
0$
#145
b11001010111111101011000100010010 #
b11001010111111101011000100010010 *
1$
#150
0$
#155
1$
#160
0$
0(
#165
0"
1$
#170
0$
#175
1$
#180
0$
b10010000101010011010100100100 '
b10010000101010011010100100100 )
1(
#185
b10010000101010011010100100100 #
b10010000101010011010100100100 *
1"
1$
#190
0$
b11000000100010010101111010000001 '
b11000000100010010101111010000001 )
#195
b11000000100010010101111010000001 #
b11000000100010010101111010000001 *
1$
#200
0$
b10000100100001001101011000001001 '
b10000100100001001101011000001001 )
#205
b10000100100001001101011000001001 #
b10000100100001001101011000001001 *
1$
#210
0$
b10110001111100000101011001100011 '
b10110001111100000101011001100011 )
#215
b10110001111100000101011001100011 #
b10110001111100000101011001100011 *
1$
#220
0$
b110101110010111101100001101 '
b110101110010111101100001101 )
#225
b110101110010111101100001101 #
b110101110010111101100001101 *
1$
#230
0$
b1000110110111111001100110001101 '
b1000110110111111001100110001101 )
#235
b1000110110111111001100110001101 #
b1000110110111111001100110001101 *
1$
#240
0$
b10110010110000101000010001100101 '
b10110010110000101000010001100101 )
#245
b10110010110000101000010001100101 #
b10110010110000101000010001100101 *
1$
#250
0$
b10001001001101110101001000010010 '
b10001001001101110101001000010010 )
#255
b10001001001101110101001000010010 #
b10001001001101110101001000010010 *
1$
#260
0$
0(
#265
0"
1$
#270
0$
#275
1$
#280
0$
#285
1$
#290
0$
0%
b11111111111111111111111111111111 '
b11111111111111111111111111111111 )
1(
#295
b11111111111111111111111111111111 +
1,
1$
#300
b0 +
0,
b0 #
b0 *
0$
0&
#304
1%
0(
1&
