rtl/wrr_arbiter.v
module wrr_arbiter #(
    parameter W1 = 1,
    parameter W2 = 2,
    parameter W3 = 4
)(
    input wire clk,
    input wire rst_n,
    input wire arb_advance, // HIGH from Crossbar FSM when ready for NEXT master
    input wire req0,
    input wire req1,
    input wire req2,
    output reg [1:0] grant        // 00=M0, 01=M1, 10=M2, 11=Idle
);

//for true round robin you should know previous grsnt 
reg [3:0] credit0;
reg [3:0] credit1;
reg [3:0] credit2;
reg [1:0] last_grant; //tracks who was served last 

//look ahead credits 
reg [3:0] c0, c1, c2;
 
//look ahead will only get reload - when request exists  , when no active request has creadit
always @(*) begin
    c0 = credit0;
    c1 = credit1;
    c2 = credit2;
    
    if ((req0 || req1 || req2) &&
        !((req0 && credit0 > 0) ||
          (req1 && credit1 > 0) ||
          (req2 && credit2 > 0))) begin
        // reload only requesting masters
        if (req0) c0 = W1;
        if (req1) c1 = W2;
        if (req2) c2 = W3;
    end
end

reg [1:0] next_grant;
always @(*) begin
    next_grant=2'b11; //default

    case(last_grant)
        //if last was M0 then m1->m2->m0
        2'b00: begin
            if(req1 && c1>0) next_grant=2'b01;
            else if (req2 && c2>0) next_grant=2'b10;
            else if (req0 && c0>0) next_grant=2'b00;
            else next_grant=2'b11;
        end
        2'b01: begin
            // last= m1 then m2->m0->m1
            if(req2 && c2>0) next_grant=2'b10;
            else if (req0 && c0>0) next_grant=2'b00;
            else if (req1 && c1>0) next_grant=2'b01;
            else next_grant=2'b11;
        end
        2'b10: begin
            //last=m2 them m0->m1_->m2
            if(req0 && c0>0) next_grant=2'b00;
            else if (req1 && c1>0) next_grant=2'b01;
            else if (req2 && c2>0) next_grant=2'b10;
            else next_grant=2'b11;
        end
        default: begin
            if(req0 && c0>0) next_grant=2'b00;
            else if (req1 && c1>0) next_grant=2'b01;
            else if (req2 && c2>0) next_grant=2'b10;
            else next_grant=2'b11;
        end
    endcase
end

always @(posedge clk or negedge rst_n) begin
    if(!rst_n) begin
        credit0 <= W1;
        credit1 <= W2;
        credit2 <= W3;
        grant <= 2'b11;
        last_grant <= 2'b11;
    end else if (arb_advance) begin
        grant <= next_grant;

        if(next_grant !=2'b11) begin
            last_grant<=next_grant;
            credit0 <=(next_grant==2'b00)?c0-1:c0;
            credit1 <= (next_grant==2'b01) ? c1-1 : c1;
            credit2 <= (next_grant==2'b10) ? c2-1 : c2;
        end else begin
            grant <= 2'b11;
            // only reload requesting masters
            if (req0) credit0 <= W1;
            if (req1) credit1 <= W2;
            if (req2) credit2 <= W3;
        end
    end
end
endmodule

tb/tb_wrr_arbiter.v
module tb_wrr_arbiter;

reg clk, rst_n;
reg arb_advance;
reg req0, req1, req2;
wire [1:0] grant;

integer cnt0, cnt1, cnt2;
integer i;

wrr_arbiter #(.W0(1),.W1(2),.W2(4)) dut (
    .clk         (clk),
    .rst_n       (rst_n),
    .arb_advance (arb_advance),
    .req0        (req0),
    .req1        (req1),
    .req2        (req2),
    .grant       (grant)
);

// clock — 10ns period
initial clk = 0;
always #5 clk = ~clk;

// task: pulse arb_advance for one cycle and read grant after settling
task do_advance;
    begin
        @(negedge clk);      // drive on negedge — safe from setup/hold
        arb_advance = 1;
        @(negedge clk);      // grant updates on posedge between these two negedges
        arb_advance = 0;
        #1;                  // let combinational settle
    end
endtask

initial begin
    $dumpfile("sim/tb_wrr.vcd");
    $dumpvars(0, tb_wrr_arbiter);

    // init
    rst_n       = 0;
    arb_advance = 0;
    req0        = 0;
    req1        = 0;
    req2        = 0;
    cnt0        = 0;
    cnt1        = 0;
    cnt2        = 0;

    // reset for 3 cycles
    repeat(3) @(negedge clk);
    rst_n = 1;
    repeat(2) @(negedge clk);

    // =========================================================
    // TEST 1: all masters requesting — check 1:2:4 ratio
    // =========================================================
    $display("========================================");
    $display("TEST 1: All masters requesting (70 grants)");
    $display("========================================");
    req0 = 1; req1 = 1; req2 = 1;
    cnt0=0; cnt1=0; cnt2=0;

    for (i=0; i<70; i=i+1) begin
        do_advance;
        case(grant)
            2'b00: cnt0 = cnt0 + 1;
            2'b01: cnt1 = cnt1 + 1;
            2'b10: cnt2 = cnt2 + 1;
            2'b11: $display("  WARNING: grant=11 during active requests at i=%0d", i);
        endcase
    end

    $display("M0 grants: %0d (expected 10)", cnt0);
    $display("M1 grants: %0d (expected 20)", cnt1);
    $display("M2 grants: %0d (expected 40)", cnt2);
    $display("Total:     %0d (expected 70)", cnt0+cnt1+cnt2);

    if (cnt0==10 && cnt1==20 && cnt2==40)
        $display("PASS: WRR ratio correct 1:2:4");
    else
        $display("FAIL: WRR ratio wrong");

    // =========================================================
    // TEST 2: grant holds when arb_advance=0
    // =========================================================
    $display("\n========================================");
    $display("TEST 2: Grant hold when arb_advance=0");
    $display("========================================");

    // get a fresh grant
    do_advance;
    begin : hold_test
        reg [1:0] held_grant;
        held_grant = grant;
        $display("Grant issued: %0b", held_grant);

        // hold arb_advance=0 for 5 cycles
        repeat(5) begin
            @(negedge clk);
            #1;
            if (grant !== held_grant)
                $display("FAIL: grant changed to %0b without arb_advance!", grant);
            else
                $display("PASS: grant=%0b held correctly", grant);
        end
    end

    // =========================================================
    // TEST 3: no requests → grant=11
    // =========================================================
    $display("\n========================================");
    $display("TEST 3: No requests → grant should be 11");
    $display("========================================");
    req0=0; req1=0; req2=0;
    do_advance;
    #1;
    if (grant == 2'b11)
        $display("PASS: grant=11 when no requests");
    else
        $display("FAIL: grant=%0b should be 11", grant);

    // =========================================================
    // TEST 4: only M0 requesting
    // =========================================================
    $display("\n========================================");
    $display("TEST 4: Only M0 requesting");
    $display("========================================");
    req0=1; req1=0; req2=0;
    cnt0=0;

    // reset first so credits reload cleanly
    rst_n=0;
    repeat(2) @(negedge clk);
    rst_n=1;
    repeat(2) @(negedge clk);

    for (i=0; i<5; i=i+1) begin
        do_advance;
        $display("grant=%0b (expected 00)", grant);
        if(grant==2'b00) cnt0=cnt0+1;
    end

    if(cnt0==5)
        $display("PASS: M0 gets all grants when alone");
    else
        $display("FAIL: M0 got %0d/5 grants", cnt0);

    // =========================================================
    // TEST 5: look-ahead — no grant=11 during credit reload
    // =========================================================
    $display("\n========================================");
    $display("TEST 5: No idle cycle during credit reload");
    $display("========================================");
    req0=1; req1=1; req2=1;

    // reset to start fresh round
    rst_n=0;
    repeat(2) @(negedge clk);
    rst_n=1;
    repeat(2) @(negedge clk);

    begin : reload_test
        integer fail_count;
        fail_count = 0;
        // run 14 grants = 2 full rounds of W0+W1+W2=7
        for (i=0; i<14; i=i+1) begin
            do_advance;
            if(grant==2'b11) begin
                $display("FAIL at grant %0d: grant went 11 during active requests!", i);
                fail_count = fail_count + 1;
            end else begin
                $display("grant[%0d]=%0b", i, grant);
            end
        end
        if(fail_count==0)
            $display("PASS: No idle cycles during reload");
    end

    // =========================================================
    // TEST 6: rotation check — print grant sequence
    // =========================================================
    $display("\n========================================");
    $display("TEST 6: Rotation sequence (1 full round)");
    $display("Expected pattern: not always same master first");
    $display("========================================");
    req0=1; req1=1; req2=1;
    rst_n=0;
    repeat(2) @(negedge clk);
    rst_n=1;
    repeat(2) @(negedge clk);

    for (i=0; i<7; i=i+1) begin
        do_advance;
        case(grant)
            2'b00: $display("  grant[%0d] = M0", i);
            2'b01: $display("  grant[%0d] = M1", i);
            2'b10: $display("  grant[%0d] = M2", i);
            2'b11: $display("  grant[%0d] = IDLE (unexpected!)", i);
        endcase
    end

    $display("\n========================================");
    $display("All tests complete");
    $display("========================================");
    $finish;
end

// timeout watchdog
initial begin
    #100000;
    $display("TIMEOUT");
    $finish;
end

endmodule

sim/tb_wrr.vcd
$date
	Sun Jun 14 23:57:07 2026
$end
$version
	Icarus Verilog
$end
$timescale
	1s
$end
$scope module tb_wrr_arbiter $end
$var wire 2 ! grant [1:0] $end
$var reg 1 " arb_advance $end
$var reg 1 # clk $end
$var reg 1 $ req0 $end
$var reg 1 % req1 $end
$var reg 1 & req2 $end
$var reg 1 ' rst_n $end
$var integer 32 ( cnt0 [31:0] $end
$var integer 32 ) cnt1 [31:0] $end
$var integer 32 * cnt2 [31:0] $end
$var integer 32 + i [31:0] $end
$scope module dut $end
$var wire 1 " arb_advance $end
$var wire 1 # clk $end
$var wire 1 $ req0 $end
$var wire 1 % req1 $end
$var wire 1 & req2 $end
$var wire 1 ' rst_n $end
$var reg 4 , c0 [3:0] $end
$var reg 4 - c1 [3:0] $end
$var reg 4 . c2 [3:0] $end
$var reg 4 / credit0 [3:0] $end
$var reg 4 0 credit1 [3:0] $end
$var reg 4 1 credit2 [3:0] $end
$var reg 2 2 grant [1:0] $end
$var reg 2 3 last_grant [1:0] $end
$var reg 2 4 next_grant [1:0] $end
$upscope $end
$scope begin hold_test $end
$var reg 2 5 held_grant [1:0] $end
$upscope $end
$scope begin reload_test $end
$var integer 32 6 fail_count [31:0] $end
$upscope $end
$scope task do_advance $end
$upscope $end
$upscope $end
$enddefinitions $end
#0
$dumpvars
bx 6
bx 5
b11 4
b11 3
b11 2
b100 1
b10 0
b1 /
b100 .
b10 -
b1 ,
bx +
b0 *
b0 )
b0 (
0'
0&
0%
0$
0#
0"
b11 !
$end
#5
1#
#10
0#
#15
1#
#20
0#
#25
1#
#30
1'
0#
#35
1#
#40
0#
#45
1#
#50
b0 4
b0 +
1&
1%
1$
0#
#55
1#
#60
1"
0#
#65
b0 ,
b1 4
b0 /
b0 3
b0 !
b0 2
1#
#70
0"
0#
#71
b1 +
b1 (
#75
1#
#80
1"
0#
#85
b1 -
b10 4
b1 0
b1 3
b1 !
b1 2
1#
#90
0"
0#
#91
b10 +
b1 )
#95
1#
#100
1"
0#
#105
b11 .
b1 4
b11 1
b10 3
b10 !
b10 2
1#
#110
0"
0#
#111
b11 +
b1 *
#115
1#
#120
1"
0#
#125
b0 -
b10 4
b0 0
b1 3
b1 !
b1 2
1#
#130
0"
0#
#131
b100 +
b10 )
#135
1#
#140
1"
0#
#145
b10 .
b10 4
b10 1
b10 3
b10 !
b10 2
1#
#150
0"
0#
#151
b101 +
b10 *
#155
1#
#160
1"
0#
#165
b10 4
b1 .
b1 1
1#
#170
0"
0#
#171
b110 +
b11 *
#175
1#
#180
1"
0#
#185
b0 4
b10 -
b1 ,
b100 .
b0 1
1#
#190
0"
0#
#191
b111 +
b100 *
#195
1#
#200
1"
0#
#205
b0 ,
b1 4
b100 1
b10 0
b0 3
b0 !
b0 2
1#
#210
0"
0#
#211
b1000 +
b10 (
#215
1#
#220
1"
0#
#225
b1 -
b10 4
b1 0
b1 3
b1 !
b1 2
1#
#230
0"
0#
#231
b1001 +
b11 )
#235
1#
#240
1"
0#
#245
b11 .
b1 4
b11 1
b10 3
b10 !
b10 2
1#
#250
0"
0#
#251
b1010 +
b101 *
#255
1#
#260
1"
0#
#265
b0 -
b10 4
b0 0
b1 3
b1 !
b1 2
1#
#270
0"
0#
#271
b1011 +
b100 )
#275
1#
#280
1"
0#
#285
b10 .
b10 4
b10 1
b10 3
b10 !
b10 2
1#
#290
0"
0#
#291
b1100 +
b110 *
#295
1#
#300
1"
0#
#305
b10 4
b1 .
b1 1
1#
#310
0"
0#
#311
b1101 +
b111 *
#315
1#
#320
1"
0#
#325
b0 4
b10 -
b1 ,
b100 .
b0 1
1#
#330
0"
0#
#331
b1110 +
b1000 *
#335
1#
#340
1"
0#
#345
b0 ,
b1 4
b100 1
b10 0
b0 3
b0 !
b0 2
1#
#350
0"
0#
#351
b1111 +
b11 (
#355
1#
#360
1"
0#
#365
b1 -
b10 4
b1 0
b1 3
b1 !
b1 2
1#
#370
0"
0#
#371
b10000 +
b101 )
#375
1#
#380
1"
0#
#385
b11 .
b1 4
b11 1
b10 3
b10 !
b10 2
1#
#390
0"
0#
#391
b10001 +
b1001 *
#395
1#
#400
1"
0#
#405
b0 -
b10 4
b0 0
b1 3
b1 !
b1 2
1#
#410
0"
0#
#411
b10010 +
b110 )
#415
1#
#420
1"
0#
#425
b10 .
b10 4
b10 1
b10 3
b10 !
b10 2
1#
#430
0"
0#
#431
b10011 +
b1010 *
#435
1#
#440
1"
0#
#445
b10 4
b1 .
b1 1
1#
#450
0"
0#
#451
b10100 +
b1011 *
#455
1#
#460
1"
0#
#465
b0 4
b10 -
b1 ,
b100 .
b0 1
1#
#470
0"
0#
#471
b10101 +
b1100 *
#475
1#
#480
1"
0#
#485
b0 ,
b1 4
b100 1
b10 0
b0 3
b0 !
b0 2
1#
#490
0"
0#
#491
b10110 +
b100 (
#495
1#
#500
1"
0#
#505
b1 -
b10 4
b1 0
b1 3
b1 !
b1 2
1#
#510
0"
0#
#511
b10111 +
b111 )
#515
1#
#520
1"
0#
#525
b11 .
b1 4
b11 1
b10 3
b10 !
b10 2
1#
#530
0"
0#
#531
b11000 +
b1101 *
#535
1#
#540
1"
0#
#545
b0 -
b10 4
b0 0
b1 3
b1 !
b1 2
1#
#550
0"
0#
#551
b11001 +
b1000 )
#555
1#
#560
1"
0#
#565
b10 .
b10 4
b10 1
b10 3
b10 !
b10 2
1#
#570
0"
0#
#571
b11010 +
b1110 *
#575
1#
#580
1"
0#
#585
b10 4
b1 .
b1 1
1#
#590
0"
0#
#591
b11011 +
b1111 *
#595
1#
#600
1"
0#
#605
b0 4
b10 -
b1 ,
b100 .
b0 1
1#
#610
0"
0#
#611
b11100 +
b10000 *
#615
1#
#620
1"
0#
#625
b0 ,
b1 4
b100 1
b10 0
b0 3
b0 !
b0 2
1#
#630
0"
0#
#631
b11101 +
b101 (
#635
1#
#640
1"
0#
#645
b1 -
b10 4
b1 0
b1 3
b1 !
b1 2
1#
#650
0"
0#
#651
b11110 +
b1001 )
#655
1#
#660
1"
0#
#665
b11 .
b1 4
b11 1
b10 3
b10 !
b10 2
1#
#670
0"
0#
#671
b11111 +
b10001 *
#675
1#
#680
1"
0#
#685
b0 -
b10 4
b0 0
b1 3
b1 !
b1 2
1#
#690
0"
0#
#691
b100000 +
b1010 )
#695
1#
#700
1"
0#
#705
b10 .
b10 4
b10 1
b10 3
b10 !
b10 2
1#
#710
0"
0#
#711
b100001 +
b10010 *
#715
1#
#720
1"
0#
#725
b10 4
b1 .
b1 1
1#
#730
0"
0#
#731
b100010 +
b10011 *
#735
1#
#740
1"
0#
#745
b0 4
b10 -
b1 ,
b100 .
b0 1
1#
#750
0"
0#
#751
b100011 +
b10100 *
#755
1#
#760
1"
0#
#765
b0 ,
b1 4
b100 1
b10 0
b0 3
b0 !
b0 2
1#
#770
0"
0#
#771
b100100 +
b110 (
#775
1#
#780
1"
0#
#785
b1 -
b10 4
b1 0
b1 3
b1 !
b1 2
1#
#790
0"
0#
#791
b100101 +
b1011 )
#795
1#
#800
1"
0#
#805
b11 .
b1 4
b11 1
b10 3
b10 !
b10 2
1#
#810
0"
0#
#811
b100110 +
b10101 *
#815
1#
#820
1"
0#
#825
b0 -
b10 4
b0 0
b1 3
b1 !
b1 2
1#
#830
0"
0#
#831
b100111 +
b1100 )
#835
1#
#840
1"
0#
#845
b10 .
b10 4
b10 1
b10 3
b10 !
b10 2
1#
#850
0"
0#
#851
b101000 +
b10110 *
#855
1#
#860
1"
0#
#865
b10 4
b1 .
b1 1
1#
#870
0"
0#
#871
b101001 +
b10111 *
#875
1#
#880
1"
0#
#885
b0 4
b10 -
b1 ,
b100 .
b0 1
1#
#890
0"
0#
#891
b101010 +
b11000 *
#895
1#
#900
1"
0#
#905
b0 ,
b1 4
b100 1
b10 0
b0 3
b0 !
b0 2
1#
#910
0"
0#
#911
b101011 +
b111 (
#915
1#
#920
1"
0#
#925
b1 -
b10 4
b1 0
b1 3
b1 !
b1 2
1#
#930
0"
0#
#931
b101100 +
b1101 )
#935
1#
#940
1"
0#
#945
b11 .
b1 4
b11 1
b10 3
b10 !
b10 2
1#
#950
0"
0#
#951
b101101 +
b11001 *
#955
1#
#960
1"
0#
#965
b0 -
b10 4
b0 0
b1 3
b1 !
b1 2
1#
#970
0"
0#
#971
b101110 +
b1110 )
#975
1#
#980
1"
0#
#985
b10 .
b10 4
b10 1
b10 3
b10 !
b10 2
1#
#990
0"
0#
#991
b101111 +
b11010 *
#995
1#
#1000
1"
0#
#1005
b10 4
b1 .
b1 1
1#
#1010
0"
0#
#1011
b110000 +
b11011 *
#1015
1#
#1020
1"
0#
#1025
b0 4
b10 -
b1 ,
b100 .
b0 1
1#
#1030
0"
0#
#1031
b110001 +
b11100 *
#1035
1#
#1040
1"
0#
#1045
b0 ,
b1 4
b100 1
b10 0
b0 3
b0 !
b0 2
1#
#1050
0"
0#
#1051
b110010 +
b1000 (
#1055
1#
#1060
1"
0#
#1065
b1 -
b10 4
b1 0
b1 3
b1 !
b1 2
1#
#1070
0"
0#
#1071
b110011 +
b1111 )
#1075
1#
#1080
1"
0#
#1085
b11 .
b1 4
b11 1
b10 3
b10 !
b10 2
1#
#1090
0"
0#
#1091
b110100 +
b11101 *
#1095
1#
#1100
1"
0#
#1105
b0 -
b10 4
b0 0
b1 3
b1 !
b1 2
1#
#1110
0"
0#
#1111
b110101 +
b10000 )
#1115
1#
#1120
1"
0#
#1125
b10 .
b10 4
b10 1
b10 3
b10 !
b10 2
1#
#1130
0"
0#
#1131
b110110 +
b11110 *
#1135
1#
#1140
1"
0#
#1145
b10 4
b1 .
b1 1
1#
#1150
0"
0#
#1151
b110111 +
b11111 *
#1155
1#
#1160
1"
0#
#1165
b0 4
b10 -
b1 ,
b100 .
b0 1
1#
#1170
0"
0#
#1171
b111000 +
b100000 *
#1175
1#
#1180
1"
0#
#1185
b0 ,
b1 4
b100 1
b10 0
b0 3
b0 !
b0 2
1#
#1190
0"
0#
#1191
b111001 +
b1001 (
#1195
1#
#1200
1"
0#
#1205
b1 -
b10 4
b1 0
b1 3
b1 !
b1 2
1#
#1210
0"
0#
#1211
b111010 +
b10001 )
#1215
1#
#1220
1"
0#
#1225
b11 .
b1 4
b11 1
b10 3
b10 !
b10 2
1#
#1230
0"
0#
#1231
b111011 +
b100001 *
#1235
1#
#1240
1"
0#
#1245
b0 -
b10 4
b0 0
b1 3
b1 !
b1 2
1#
#1250
0"
0#
#1251
b111100 +
b10010 )
#1255
1#
#1260
1"
0#
#1265
b10 .
b10 4
b10 1
b10 3
b10 !
b10 2
1#
#1270
0"
0#
#1271
b111101 +
b100010 *
#1275
1#
#1280
1"
0#
#1285
b10 4
b1 .
b1 1
1#
#1290
0"
0#
#1291
b111110 +
b100011 *
#1295
1#
#1300
1"
0#
#1305
b0 4
b10 -
b1 ,
b100 .
b0 1
1#
#1310
0"
0#
#1311
b111111 +
b100100 *
#1315
1#
#1320
1"
0#
#1325
b0 ,
b1 4
b100 1
b10 0
b0 3
b0 !
b0 2
1#
#1330
0"
0#
#1331
b1000000 +
b1010 (
#1335
1#
#1340
1"
0#
#1345
b1 -
b10 4
b1 0
b1 3
b1 !
b1 2
1#
#1350
0"
0#
#1351
b1000001 +
b10011 )
#1355
1#
#1360
1"
0#
#1365
b11 .
b1 4
b11 1
b10 3
b10 !
b10 2
1#
#1370
0"
0#
#1371
b1000010 +
b100101 *
#1375
1#
#1380
1"
0#
#1385
b0 -
b10 4
b0 0
b1 3
b1 !
b1 2
1#
#1390
0"
0#
#1391
b1000011 +
b10100 )
#1395
1#
#1400
1"
0#
#1405
b10 .
b10 4
b10 1
b10 3
b10 !
b10 2
1#
#1410
0"
0#
#1411
b1000100 +
b100110 *
#1415
1#
#1420
1"
0#
#1425
b10 4
b1 .
b1 1
1#
#1430
0"
0#
#1431
b1000101 +
b100111 *
#1435
1#
#1440
1"
0#
#1445
b0 4
b10 -
b1 ,
b100 .
b0 1
1#
#1450
0"
0#
#1451
b1000110 +
b101000 *
#1455
1#
#1460
1"
0#
#1465
b0 ,
b1 4
b100 1
b10 0
b0 3
b0 !
b0 2
1#
#1470
0"
0#
#1471
b0 5
#1475
1#
#1480
0#
#1485
1#
#1490
0#
#1495
1#
#1500
0#
#1505
1#
#1510
0#
#1515
1#
#1520
0#
#1521
b11 4
0&
0%
0$
#1525
1#
#1530
1"
0#
#1535
b11 !
b11 2
1#
#1540
0"
0#
#1542
b11 3
b1 /
b0 4
b1 ,
0'
b0 (
1$
#1545
1#
#1550
0#
#1555
1#
#1560
1'
0#
#1565
1#
#1570
0#
#1575
1#
#1580
b0 +
0#
#1585
1#
#1590
1"
0#
#1595
b1 ,
b0 4
b0 /
b0 3
b0 !
b0 2
1#
#1600
0"
0#
#1601
b1 +
b1 (
#1605
1#
#1610
1"
0#
#1615
1#
#1620
0"
0#
#1621
b10 +
b10 (
#1625
1#
#1630
1"
0#
#1635
1#
#1640
0"
0#
#1641
b11 +
b11 (
#1645
1#
#1650
1"
0#
#1655
1#
#1660
0"
0#
#1661
b100 +
b100 (
#1665
1#
#1670
1"
0#
#1675
1#
#1680
0"
0#
#1681
b11 3
b11 !
b11 2
b1 /
b0 4
b1 ,
0'
1&
1%
b101 +
b101 (
#1685
1#
#1690
0#
#1695
1#
#1700
1'
0#
#1705
1#
#1710
0#
#1715
1#
#1720
b0 +
b0 6
0#
#1725
1#
#1730
1"
0#
#1735
b0 ,
b1 4
b0 /
b0 3
b0 !
b0 2
1#
#1740
0"
0#
#1741
b1 +
#1745
1#
#1750
1"
0#
#1755
b1 -
b10 4
b1 0
b1 3
b1 !
b1 2
1#
#1760
0"
0#
#1761
b10 +
#1765
1#
#1770
1"
0#
#1775
b11 .
b1 4
b11 1
b10 3
b10 !
b10 2
1#
#1780
0"
0#
#1781
b11 +
#1785
1#
#1790
1"
0#
#1795
b0 -
b10 4
b0 0
b1 3
b1 !
b1 2
1#
#1800
0"
0#
#1801
b100 +
#1805
1#
#1810
1"
0#
#1815
b10 .
b10 4
b10 1
b10 3
b10 !
b10 2
1#
#1820
0"
0#
#1821
b101 +
#1825
1#
#1830
1"
0#
#1835
b10 4
b1 .
b1 1
1#
#1840
0"
0#
#1841
b110 +
#1845
1#
#1850
1"
0#
#1855
b0 4
b10 -
b1 ,
b100 .
b0 1
1#
#1860
0"
0#
#1861
b111 +
#1865
1#
#1870
1"
0#
#1875
b0 ,
b1 4
b100 1
b10 0
b0 3
b0 !
b0 2
1#
#1880
0"
0#
#1881
b1000 +
#1885
1#
#1890
1"
0#
#1895
b1 -
b10 4
b1 0
b1 3
b1 !
b1 2
1#
#1900
0"
0#
#1901
b1001 +
#1905
1#
#1910
1"
0#
#1915
b11 .
b1 4
b11 1
b10 3
b10 !
b10 2
1#
#1920
0"
0#
#1921
b1010 +
#1925
1#
#1930
1"
0#
#1935
b0 -
b10 4
b0 0
b1 3
b1 !
b1 2
1#
#1940
0"
0#
#1941
b1011 +
#1945
1#
#1950
1"
0#
#1955
b10 .
b10 4
b10 1
b10 3
b10 !
b10 2
1#
#1960
0"
0#
#1961
b1100 +
#1965
1#
#1970
1"
0#
#1975
b10 4
b1 .
b1 1
1#
#1980
0"
0#
#1981
b1101 +
#1985
1#
#1990
1"
0#
#1995
b0 4
b10 -
b1 ,
b100 .
b0 1
1#
#2000
0"
0#
#2001
b0 4
b11 3
b11 !
b11 2
b100 1
b10 0
b1 /
0'
b1110 +
#2005
1#
#2010
0#
#2015
1#
#2020
1'
0#
#2025
1#
#2030
0#
#2035
1#
#2040
b0 +
0#
#2045
1#
#2050
1"
0#
#2055
b0 ,
b1 4
b0 /
b0 3
b0 !
b0 2
1#
#2060
0"
0#
#2061
b1 +
#2065
1#
#2070
1"
0#
#2075
b1 -
b10 4
b1 0
b1 3
b1 !
b1 2
1#
#2080
0"
0#
#2081
b10 +
#2085
1#
#2090
1"
0#
#2095
b11 .
b1 4
b11 1
b10 3
b10 !
b10 2
1#
#2100
0"
0#
#2101
b11 +
#2105
1#
#2110
1"
0#
#2115
b0 -
b10 4
b0 0
b1 3
b1 !
b1 2
1#
#2120
0"
0#
#2121
b100 +
#2125
1#
#2130
1"
0#
#2135
b10 .
b10 4
b10 1
b10 3
b10 !
b10 2
1#
#2140
0"
0#
#2141
b101 +
#2145
1#
#2150
1"
0#
#2155
b10 4
b1 .
b1 1
1#
#2160
0"
0#
#2161
b110 +
#2165
1#
#2170
1"
0#
#2175
b0 4
b10 -
b1 ,
b100 .
b0 1
1#
#2180
0"
0#
#2181
b111 +
